MANIFEST.in
Pipfile
README.md
setup.py
scripts/write-vault-environment
src/tests/__init__.py
src/tests/test_uri.py
src/tests/test_vault_environment.py
src/vault_tools/__init__.py
src/vault_tools/entrypoints.py
src/vault_tools/environment.py
src/vault_tools/refresh.py
src/vault_tools/settings.py
src/vault_tools/uri.py
src/vault_tools.egg-info/PKG-INFO
src/vault_tools.egg-info/SOURCES.txt
src/vault_tools.egg-info/dependency_links.txt
src/vault_tools.egg-info/entry_points.txt
src/vault_tools.egg-info/requires.txt
src/vault_tools.egg-info/top_level.txt