Metadata-Version: 2.1
Name: vault-tools
Version: 0.1.1
Summary: misc tools to work with vault
Home-page: https://github.com/openslate/vault-tools
Author: OpenSlate
Author-email: code@openslate.com
License: UNKNOWN
Platform: UNKNOWN
